{
  "product_id_lookup": {
    "telephone system": [
      "193",
      "772",
      "764",
      "139",
      "783"
    ],
    "telephone instrument": [
      "20448",
      "20540",
      "20579",
      "20639",
      "20696",
      "20753"
    ],
    "telephone": [
      "181",
      "681",
      "816",
      "518",
      "576"
    ],
    "telecommunication system": [
      "14203",
      "18336",
      "22435",
      "36100"
    ],
    "analogue meter": [
      "181",
      "191",
      "811",
      "818",
      "590"
    ],
    "sound power telephone": [
      "23968",
      "22937",
      "22936",
      "22935",
      "27933"
    ],
    "conventional relay & control panel": [
      "38185",
      "38198",
      "38206",
      "38387"
    ],
    "telecom package": [
      "14004",
      "19206",
      "19262",
      "18697",
      "19229",
      "19218",
      "20983",
      "22436",
      "22704",
      "23211"
    ],
    "internal telephone exchange servicing": [
      "243",
      "572",
      "686",
      "724",
      "356"
    ],
    "auto telephone system": [
      "23967",
      "22940",
      "22939",
      "22938",
      "27057",
      "22941"
    ],
    "hi-lo pilots (indicating dial type)": [
      "13816",
      "38324",
      "35544",
      "36103"
    ],
    "signal distributors": [
      "13943",
      "15212",
      "20873",
      "22615"
    ],
    "dial thermometer": [
      "220",
      "132",
      "203",
      "522",
      "051"
    ],
    "telephone cable": [
      "13984",
      "20103",
      "20071",
      "24070",
      "21238",
      "23922"
    ],
    "interposing relays": [
      "137",
      "572",
      "030",
      "523",
      "679"
    ],
    "relay & control panel": [
      "6389",
      "5560",
      "11172",
      "11457",
      "7888",
      "19357",
      "24445",
      "24450",
      "24448",
      "24827",
      "24815",
      "24451",
      "19363",
      "24930",
      "24941",
      "38203",
      "38204"
    ],
    "relays": [
      "5939",
      "6768",
      "7908",
      "12286",
      "8231",
      "12095",
      "12177",
      "12706",
      "22295",
      "34802"
    ],
    "buchholz relay": [
      "64",
      "425",
      "612"
    ],
    "paging and intercom system - offshore": [
      "6431",
      "5601",
      "39444",
      "39507",
      "39552"
    ],
    "interface devices": [
      "6630",
      "5800",
      "11596",
      "11597",
      "10310",
      "11701",
      "11702",
      "11703",
      "12288",
      "8405",
      "13108",
      "13117",
      "21089",
      "21081",
      "21077",
      "21070"
    ],
    "digital indicator": [
      "1",
      "365",
      "123",
      "180"
    ],
    "electrical terminals": [
      "21153",
      "21157",
      "28575",
      "36610"
    ],
    "speaker": [
      "139",
      "852",
      "101",
      "035",
      "052"
    ],
    "disposal level transmitters": [
      "17087",
      "17086",
      "17996",
      "17997",
      "18641"
    ],
    "on-off valves": [
      "6494",
      "5665",
      "11273",
      "11719",
      "9263",
      "8149",
      "8160",
      "8188",
      "8187",
      "8386",
      "8597",
      "8693",
      "8669",
      "8674",
      "8688",
      "12185",
      "12293",
      "12610",
      "12821",
      "12914",
      "12934",
      "12959",
      "12969",
      "12925",
      "12935",
      "12957",
      "12961",
      "12967",
      "12968",
      "12970",
      "16129",
      "16458",
      "18305",
      "18468",
      "18462",
      "18451",
      "18447",
      "18444",
      "19712",
      "23746",
      "21621",
      "21764",
      "25964",
      "28149",
      "28148",
      "28147",
      "31883",
      "37526",
      "34316",
      "36255",
      "36408"
    ],
    "wireless communication equipment": [
      "7073",
      "7400",
      "18829",
      "18864"
    ],
    "indicating meters": [
      "13682",
      "14947",
      "19149",
      "19123",
      "19142"
    ],
    "level transmitter": [
      "14042",
      "36533",
      "17995",
      "18211",
      "19929",
      "19985",
      "19983",
      "36512",
      "40096"
    ],
    "auxiliary relay": [
      "2",
      "013",
      "420",
      "111"
    ],
    "signal isolators": [
      "197",
      "521",
      "975",
      "327",
      "080"
    ]
  }
}