{
  "flat_stage2_results": [
    {
      "retrieval_score": 0.8955316,
      "text": "core_product_name: armoured cable | type_or_class: Power | construction_features: Armour",
      "core_id": 130.0,
      "raw_product_name": "ARMOURED CABLE-(POWER)",
      "list_of_product_ids": [
        "8891",
        "8910",
        "8938",
        "8942",
        "8950",
        "8946",
        "8954",
        "9083",
        "9087",
        "9091",
        "9095",
        "9099",
        "23875",
        "24038",
        "24687",
        "24728",
        "24957",
        "27122",
        "27117",
        "27126",
        "27130",
        "27134",
        "27161",
        "27166",
        "27171",
        "27180",
        "27284",
        "27336",
        "27357",
        "27397",
        "27432",
        "27519",
        "27525",
        "27538",
        "27543",
        "27552",
        "27579",
        "27637",
        "27645",
        "27681",
        "27672",
        "27770",
        "27788",
        "27809",
        "27899",
        "27916",
        "27961",
        "28027",
        "28079",
        "28068",
        "28144",
        "28114",
        "28110",
        "28106",
        "28270",
        "28282",
        "28294",
        "28290",
        "28349",
        "28384",
        "28380",
        "28412",
        "28420",
        "28457",
        "28454",
        "28465",
        "28497",
        "28513",
        "39980",
        "39981",
        "39982",
        "39983",
        "40102",
        "40105",
        "40106",
        "40103",
        "40104",
        "40107",
        "40108",
        "40109"
      ]
    },
    {
      "retrieval_score": 0.8927831,
      "text": "core_product_name: armoured cable | construction_features: Armour | special_attributes: Loop",
      "core_id": 130.0,
      "raw_product_name": "ARMOURED CABLE-(LOOP)",
      "list_of_product_ids": [
        "9936",
        "9937",
        "9938",
        "8890",
        "8911",
        "8937",
        "8941",
        "8949",
        "8945",
        "8953",
        "9082",
        "9086",
        "9090",
        "9094",
        "9098",
        "19456",
        "19459",
        "19521",
        "19532",
        "19549",
        "19556",
        "23874",
        "24037",
        "24686",
        "27123",
        "27118",
        "27127",
        "27131",
        "27135",
        "27162",
        "27167",
        "27172",
        "27181",
        "27283",
        "27337",
        "27358",
        "27398",
        "27433",
        "27520",
        "27526",
        "27539",
        "27544",
        "27553",
        "27580",
        "27638",
        "27646",
        "27682",
        "27673",
        "27771",
        "27789",
        "27810",
        "27900",
        "27917",
        "27962",
        "28028",
        "28080",
        "28067",
        "28145",
        "28115",
        "28111",
        "28107",
        "28271",
        "28283",
        "28295",
        "28291",
        "28347",
        "28385",
        "28381",
        "28413",
        "28419",
        "28458",
        "28455",
        "28466",
        "28498",
        "28514",
        "38762",
        "38596",
        "38683",
        "38622",
        "38711",
        "38650",
        "38736",
        "38847",
        "38879",
        "38921",
        "38947",
        "38984",
        "39011",
        "39039",
        "39064",
        "39107",
        "39137",
        "39185",
        "39213",
        "39266",
        "39287",
        "39333",
        "39369",
        "39398",
        "39428",
        "39479",
        "39534",
        "39561",
        "38788",
        "39599",
        "39623",
        "39651",
        "39685",
        "39725",
        "39795",
        "39823",
        "39894"
      ]
    },
    {
      "retrieval_score": 0.88815093,
      "text": "core_product_name: armoured cable | type_or_class: Speaker | construction_features: Armour",
      "core_id": 130.0,
      "raw_product_name": "ARMOURED CABLE-(SPEAKER)",
      "list_of_product_ids": [
        "8892",
        "8909",
        "8939",
        "8943",
        "8951",
        "8947",
        "8955",
        "9084",
        "9088",
        "9092",
        "9096",
        "9100",
        "23876",
        "24039",
        "24688",
        "24727",
        "24956",
        "27121",
        "27116",
        "27125",
        "27129",
        "27133",
        "27160",
        "27165",
        "27170",
        "27179",
        "27285",
        "27335",
        "27356",
        "27396",
        "27431",
        "27518",
        "27524",
        "27537",
        "27542",
        "27551",
        "27578",
        "27636",
        "27644",
        "27680",
        "27671",
        "27769",
        "27787",
        "27808",
        "27898",
        "27915",
        "27960",
        "28026",
        "28078",
        "28066",
        "28143",
        "28113",
        "28109",
        "28105",
        "28269",
        "28281",
        "28289",
        "28293",
        "28346",
        "28383",
        "28379",
        "28411",
        "28421",
        "28453",
        "28456",
        "28464",
        "28496",
        "28512"
      ]
    },
    {
      "retrieval_score": 0.8737344,
      "text": "core_product_name: cable | material: Copper",
      "core_id": 1.0,
      "raw_product_name": "CABLE -COPPER",
      "list_of_product_ids": [
        "32910",
        "32911",
        "33009",
        "33041",
        "33195",
        "33260",
        "33562",
        "33633",
        "35922"
      ]
    },
    {
      "retrieval_score": 0.8674297,
      "text": "core_product_name: screened cable | special_attributes: Screened cable",
      "core_id": 1976.0,
      "raw_product_name": "SCREENED CABLES",
      "list_of_product_ids": [
        "13881",
        "14838",
        "15808",
        "20059",
        "20100",
        "24067",
        "23919"
      ]
    },
    {
      "retrieval_score": 0.8644566,
      "text": "core_product_name: instrumentation cable | special_attributes: Screened",
      "core_id": 1262.0,
      "raw_product_name": "INSTRUMENTATION CABLES (SCREENED)",
      "list_of_product_ids": [
        "19885",
        "19880",
        "24078",
        "23930",
        "27348"
      ]
    },
    {
      "retrieval_score": 0.86112314,
      "text": "core_product_name: tube | material: Copper | construction_features: Coated | construction_features: Bare",
      "core_id": 88.0,
      "raw_product_name": "COPPER TUBES(COATED,BARE)",
      "list_of_product_ids": [
        "6",
        "487",
        "565",
        "818",
        "967"
      ]
    },
    {
      "retrieval_score": 0.8606609,
      "text": "core_product_name: tube | material: Copper and Alloys",
      "core_id": 88.0,
      "raw_product_name": "TUBE COPPER AND ALLOYS",
      "list_of_product_ids": [
        "6308",
        "5479",
        "8815",
        "8816",
        "31806"
      ]
    },
    {
      "retrieval_score": 0.85926664,
      "text": "core_product_name: wire | material: Copper | construction_features: Conductor | material: PVC (Polyvinyl Chloride) | construction_features: Insulated",
      "core_id": 313.0,
      "raw_product_name": "COPPER CONDUCTOR PVC INSULATED WIRES",
      "list_of_product_ids": [
        "140",
        "901",
        "478",
        "121",
        "282"
      ]
    },
    {
      "retrieval_score": 0.8586477,
      "text": "core_product_name: electric wire | material: Copper",
      "core_id": 688.0,
      "raw_product_name": "ELECTRIC COPPER WIRE",
      "list_of_product_ids": [
        "211",
        "542",
        "115",
        "028",
        "492"
      ]
    },
    {
      "retrieval_score": 0.8585772,
      "text": "core_product_name: solid conductor | material: Copper",
      "core_id": 2063.0,
      "raw_product_name": "SOLID COPPER CONDUCTOR",
      "list_of_product_ids": [
        "180",
        "781",
        "807",
        "918",
        "591"
      ]
    },
    {
      "retrieval_score": 0.85617006,
      "text": "core_product_name: seal | material: Copper",
      "core_id": 487.0,
      "raw_product_name": "COPPER SEAL",
      "list_of_product_ids": [
        "214",
        "332",
        "143",
        "227",
        "055"
      ]
    },
    {
      "retrieval_score": 0.8558488,
      "text": "core_product_name: control cable | protection_features: Fire Survival",
      "core_id": 4.0,
      "raw_product_name": "CONTROL CABLE - FIRE SURVIVAL",
      "list_of_product_ids": [
        "6424",
        "5594",
        "10194",
        "10666",
        "11369",
        "11371",
        "12120",
        "13290",
        "15814",
        "17323",
        "17783",
        "23993",
        "23862"
      ]
    },
    {
      "retrieval_score": 0.85460156,
      "text": "core_product_name: special cable",
      "core_id": 2074.0,
      "raw_product_name": "SPECIAL CABLES",
      "list_of_product_ids": [
        "13989",
        "14840",
        "20102",
        "20070",
        "24071",
        "23923"
      ]
    },
    {
      "retrieval_score": 0.85422695,
      "text": "core_product_name: cable",
      "core_id": 1.0,
      "raw_product_name": "CABLES",
      "list_of_product_ids": [
        "15455",
        "13721",
        "24275",
        "15161",
        "16241",
        "19098",
        "23820",
        "23814",
        "21319",
        "19315",
        "23819",
        "23822",
        "24273",
        "23829",
        "20141",
        "23831",
        "24058",
        "23836",
        "23909",
        "23839",
        "23828",
        "24685",
        "24726",
        "24844",
        "24955",
        "31590",
        "31591",
        "26436",
        "26438",
        "31740",
        "33330"
      ]
    },
    {
      "retrieval_score": 0.854132,
      "text": "core_product_name: cable",
      "core_id": 1.0,
      "raw_product_name": "CABLE STOCKIST/TRADERS",
      "list_of_product_ids": [
        "2",
        "467",
        "924",
        "680"
      ]
    },
    {
      "retrieval_score": 0.8537834,
      "text": "core_product_name: compensating cable",
      "core_id": 407.0,
      "raw_product_name": "COMPENSATING CABLE",
      "list_of_product_ids": [
        "24082",
        "21244",
        "21234",
        "23933",
        "28345"
      ]
    },
    {
      "retrieval_score": 0.8534463,
      "text": "core_product_name: signal cable | protection_features: Fire Resistant",
      "core_id": 826.0,
      "raw_product_name": "SIGNAL CABLE - FIRE RESISTANT",
      "list_of_product_ids": [
        "6482",
        "5653",
        "10413",
        "10664",
        "12117",
        "13288",
        "13294",
        "17776",
        "17788",
        "23870",
        "24034",
        "38767",
        "38585",
        "38611",
        "38690",
        "38715",
        "38639",
        "38826",
        "38662",
        "38858",
        "38900",
        "38926",
        "38741",
        "38963",
        "38990",
        "39018",
        "39047",
        "39086",
        "39116",
        "39162",
        "39206",
        "39245",
        "39280",
        "39326",
        "39362",
        "39391",
        "39421",
        "39472",
        "39554",
        "39527",
        "39616",
        "39592",
        "39644",
        "39678",
        "39718",
        "39788",
        "39816",
        "39887"
      ]
    },
    {
      "retrieval_score": 0.850965,
      "text": "core_product_name: instrumentation cable | type_or_class: Paired",
      "core_id": 1262.0,
      "raw_product_name": "INSTRUMENTATION CABLES (PAIRED)",
      "list_of_product_ids": [
        "19886",
        "19882",
        "24079",
        "23913",
        "27347"
      ]
    },
    {
      "retrieval_score": 0.85005933,
      "text": "core_product_name: tube | material: Copper | construction_features: PVC (Polyvinyl Chloride) coated",
      "core_id": 88.0,
      "raw_product_name": "COPPER TUBE (PVC COATED)",
      "list_of_product_ids": [
        "16380",
        "16442",
        "16464",
        "16437"
      ]
    },
    {
      "retrieval_score": 0.8495524,
      "text": "core_product_name: commercial cable",
      "core_id": 400.0,
      "raw_product_name": "COMMERCIAL CABLE",
      "list_of_product_ids": [
        "20779",
        "20808",
        "20806",
        "21176",
        "21175",
        "27361"
      ]
    },
    {
      "retrieval_score": 0.8494301,
      "text": "core_product_name: power cable",
      "core_id": 3.0,
      "raw_product_name": "POWER CABLE",
      "list_of_product_ids": [
        "13440",
        "14645",
        "15813",
        "29442",
        "29447",
        "29448",
        "24045",
        "23896",
        "36583",
        "36611",
        "38139"
      ]
    },
    {
      "retrieval_score": 0.8476675,
      "text": "core_product_name: copper pipe",
      "core_id": 486.0,
      "raw_product_name": "COPPER PIPE",
      "list_of_product_ids": [
        "757",
        "172",
        "467",
        "754"
      ]
    },
    {
      "retrieval_score": 0.8473147,
      "text": "core_product_name: flexible wire | material: Copper",
      "core_id": 912.0,
      "raw_product_name": "FLEXIBLE COPPER WIRES",
      "list_of_product_ids": [
        "136",
        "081",
        "478",
        "520",
        "094"
      ]
    },
    {
      "retrieval_score": 0.84724194,
      "text": "core_product_name: primary structure | construction_features: welded",
      "core_id": 223.0,
      "raw_product_name": "BOILER PRIMARY STRUCTURE(WELDED)",
      "list_of_product_ids": [
        "19999",
        "20036",
        "22016",
        "21003",
        "21084",
        "21900",
        "22115",
        "21039",
        "19993",
        "22825",
        "22991"
      ]
    },
    {
      "retrieval_score": 0.8463874,
      "text": "core_product_name: primary structure | construction_features: bolted",
      "core_id": 223.0,
      "raw_product_name": "BOILER PRIMARY STRUCTURE(BOLTED)",
      "list_of_product_ids": [
        "20000",
        "19997",
        "20035",
        "21038",
        "21002",
        "21083",
        "21901",
        "22017",
        "22116",
        "22826",
        "22992"
      ]
    },
    {
      "retrieval_score": 0.84624624,
      "text": "core_product_name: fire survival cable | protection_features: Fire Survival",
      "core_id": 998.0,
      "raw_product_name": "Fire Survival Cables",
      "list_of_product_ids": [
        "18687",
        "18691",
        "18690",
        "18689",
        "18688",
        "19017",
        "24074",
        "21256",
        "21579",
        "21615",
        "21624",
        "21596",
        "23926",
        "38742",
        "38663",
        "38768",
        "36637",
        "38586",
        "38127",
        "38612",
        "38136",
        "38716",
        "38640",
        "38827",
        "38859",
        "38901",
        "38927",
        "38691",
        "38964",
        "38991",
        "39019",
        "39048",
        "39087",
        "39117",
        "39164",
        "39207",
        "39246",
        "39281",
        "39327",
        "39363",
        "39392",
        "39422",
        "39473",
        "39528",
        "39555",
        "39593",
        "39617",
        "39645",
        "39679",
        "39719",
        "39789",
        "39817",
        "39888"
      ]
    },
    {
      "retrieval_score": 0.8450839,
      "text": "core_product_name: cable | material: Rubber",
      "core_id": 1.0,
      "raw_product_name": "RUBBER CABLES",
      "list_of_product_ids": [
        "38749",
        "38955",
        "38670",
        "38589",
        "38533",
        "38534",
        "38615",
        "38698",
        "38775",
        "38723",
        "38643",
        "38834",
        "38866",
        "38908",
        "38934",
        "38971",
        "38998",
        "39026",
        "39060",
        "39094",
        "39124",
        "39172",
        "39225",
        "39253",
        "39295",
        "39345",
        "39381",
        "39410",
        "39440",
        "39456",
        "39491",
        "39546",
        "39573",
        "39611",
        "39635",
        "39663",
        "39697",
        "39737",
        "39807",
        "39835",
        "39906"
      ]
    },
    {
      "retrieval_score": 0.84474903,
      "text": "core_product_name: welding cable",
      "core_id": 2458.0,
      "raw_product_name": "WELDING CABLE",
      "list_of_product_ids": [
        "32845",
        "32846",
        "33000",
        "33033",
        "33187",
        "33252",
        "33555",
        "33626",
        "35915"
      ]
    },
    {
      "retrieval_score": 0.84451556,
      "text": "core_product_name: naval cable",
      "core_id": 1533.0,
      "raw_product_name": "NAVAL CABLE",
      "list_of_product_ids": [
        "20820",
        "20818",
        "20816",
        "20814",
        "20812",
        "20810",
        "21172",
        "21170",
        "27353"
      ]
    }
  ]
}